odoo/addons/stock_vertical_lift_kardex/README.rst
odoo/addons/stock_vertical_lift_kardex/__init__.py
odoo/addons/stock_vertical_lift_kardex/__manifest__.py
odoo/addons/stock_vertical_lift_kardex/requirements.txt
odoo/addons/stock_vertical_lift_kardex/i18n/it.po
odoo/addons/stock_vertical_lift_kardex/i18n/stock_vertical_lift_kardex.pot
odoo/addons/stock_vertical_lift_kardex/models/__init__.py
odoo/addons/stock_vertical_lift_kardex/models/stock_location.py
odoo/addons/stock_vertical_lift_kardex/models/vertical_lift_shuttle.py
odoo/addons/stock_vertical_lift_kardex/proxy/README.rst
odoo/addons/stock_vertical_lift_kardex/proxy/kardex-proxy.py
odoo/addons/stock_vertical_lift_kardex/proxy/requirements.txt
odoo/addons/stock_vertical_lift_kardex/proxy/test.py
odoo/addons/stock_vertical_lift_kardex/readme/CONTRIBUTORS.md
odoo/addons/stock_vertical_lift_kardex/readme/CREDITS.md
odoo/addons/stock_vertical_lift_kardex/readme/DESCRIPTION.md
odoo/addons/stock_vertical_lift_kardex/readme/ROADMAP.md
odoo/addons/stock_vertical_lift_kardex/static/description/icon.png
odoo/addons/stock_vertical_lift_kardex/static/description/index.html
odoo_addon_stock_vertical_lift_kardex-18.0.1.0.0.3.dist-info/METADATA
odoo_addon_stock_vertical_lift_kardex-18.0.1.0.0.3.dist-info/WHEEL
odoo_addon_stock_vertical_lift_kardex-18.0.1.0.0.3.dist-info/top_level.txt
odoo_addon_stock_vertical_lift_kardex-18.0.1.0.0.3.dist-info/RECORD
